Metadata-Version: 2.1
Name: django-background-tasks4
Version: 1.3.0
Summary: Database backed asynchronous task queue
Home-page: http://github.com/arteria/django-background-tasks4
Author: spbsoluble
Author-email: spbsoluble-noreply@github.com
License: BSD
Classifier: Development Status :: 5 - Production/Stable
Classifier: Environment :: Web Environment
Classifier: Intended Audience :: Developers
Classifier: License :: OSI Approved :: BSD License
Classifier: Operating System :: OS Independent
Classifier: Topic :: Software Development :: Libraries :: Python Modules
Classifier: Framework :: Django
Classifier: Framework :: Django :: 1.8
Classifier: Framework :: Django :: 1.11
Classifier: Framework :: Django :: 2.0
Classifier: Framework :: Django :: 2.1
Classifier: Programming Language :: Python
Classifier: Programming Language :: Python :: 2
Classifier: Programming Language :: Python :: 2.7
Classifier: Programming Language :: Python :: 3
Classifier: Programming Language :: Python :: 3.4
Classifier: Programming Language :: Python :: 3.5
Classifier: Programming Language :: Python :: 3.6
Classifier: Programming Language :: Python :: 3.7
License-File: LICENSE
License-File: AUTHORS.txt
Requires-Dist: django-compat (>=1.0.13)
Requires-Dist: six
